FileSequence/FileSequence.py
FileSequence/FrameRange.py
FileSequence/FrameSet.py
FileSequence/__init__.py
opencue/__init__.py
opencue/api.py
opencue/config.py
opencue/cuebot.py
opencue/default.yaml
opencue/exception.py
opencue/search.py
opencue/util.py
opencue/version.py
opencue/wrappers/__init__.py
opencue/wrappers/allocation.py
opencue/wrappers/comment.py
opencue/wrappers/deed.py
opencue/wrappers/depend.py
opencue/wrappers/filter.py
opencue/wrappers/frame.py
opencue/wrappers/group.py
opencue/wrappers/host.py
opencue/wrappers/job.py
opencue/wrappers/layer.py
opencue/wrappers/limit.py
opencue/wrappers/owner.py
opencue/wrappers/proc.py
opencue/wrappers/render_partition.py
opencue/wrappers/service.py
opencue/wrappers/show.py
opencue/wrappers/subscription.py
opencue/wrappers/task.py
opencue/wrappers/util.py
opencue_pycue-1.13.8.dist-info/METADATA
opencue_pycue-1.13.8.dist-info/WHEEL
opencue_pycue-1.13.8.dist-info/RECORD
