Metadata-Version: 2.1
Name: opencue_pycue
Version: 1.13.8
Summary: PyCue is the Python API client for OpenCue, providing programmatic access to core services. It enables developers to query, submit, and control jobs, layers, and frames directly from Python code.
Requires-Python: >3.7
Requires-Dist: future==1.0.0
Requires-Dist: opencue-proto
Requires-Dist: pyyaml==6.0.1
Requires-Dist: six==1.16.0
Provides-Extra: test
Requires-Dist: mock==2.0.0; extra == 'test'
Requires-Dist: pyfakefs==5.2.3; extra == 'test'
Requires-Dist: pytest; extra == 'test'
